ocrLangModel4uts/__init__.py
ocrLangModel4uts/data/english_g2.pth
ocrLangModel4uts/data/zh_sim_g2.pth
ocrLangModel4uts-1.0.1.dist-info/METADATA
ocrLangModel4uts-1.0.1.dist-info/WHEEL
ocrLangModel4uts-1.0.1.dist-info/top_level.txt
ocrLangModel4uts-1.0.1.dist-info/RECORD
